Workbook

Sheet Sales_Data
A1: Order_ID | B1: Order_Date | C1: Region | D1: Product | E1: Category | F1: Units_Sold | G1: Unit_Price | H1: Unit_Cost | I1: Revenue | J1: Total_Cost | K1: Profit | L1: Profit_Margin
A2: 1001 | B2: 46027 | C2: North | D2: Laptop | E2: Electronics | F2: 2 | G2: 50000 | H2: 38000 | I2: =F2*G2 -> 100000 | J2: =F2*H2 -> 76000 | K2: =I2-J2 -> 24000 | L2: =IFERROR(K2/I2,0) -> 0.24
A3: 1002 | B3: 46034 | C3: South | D3: Headphones | E3: Accessories | F3: 10 | G3: 2000 | H3: 1200 | I3: =F3*G3 -> 20000 | J3: =F3*H3 -> 12000 | K3: =I3-J3 -> 8000 | L3: =IFERROR(K3/I3,0) -> 0.4
A4: 1003 | B4: 46040 | C4: East | D4: Keyboard | E4: Accessories | F4: 8 | G4: 1500 | H4: 900 | I4: =F4*G4 -> 12000 | J4: =F4*H4 -> 7200 | K4: =I4-J4 -> 4800 | L4: =IFERROR(K4/I4,0) -> 0.4
A5: 1004 | B5: 46056 | C5: West | D5: Laptop | E5: Electronics | F5: 3 | G5: 50000 | H5: 38000 | I5: =F5*G5 -> 150000 | J5: =F5*H5 -> 114000 | K5: =I5-J5 -> 36000 | L5: =IFERROR(K5/I5,0) -> 0.24
A6: 1005 | B6: 46063 | C6: North | D6: Mouse | E6: Accessories | F6: 15 | G6: 800 | H6: 400 | I6: =F6*G6 -> 12000 | J6: =F6*H6 -> 6000 | K6: =I6-J6 -> 6000 | L6: =IFERROR(K6/I6,0) -> 0.5
A7: 1006 | B7: 46072 | C7: South | D7: Monitor | E7: Electronics | F7: 4 | G7: 12000 | H7: 8500 | I7: =F7*G7 -> 48000 | J7: =F7*H7 -> 34000 | K7: =I7-J7 -> 14000 | L7: =IFERROR(K7/I7,0) -> 0.29166667
A8: 1007 | B8: 46083 | C8: East | D8: Laptop | E8: Electronics | F8: 1 | G8: 50000 | H8: 38000 | I8: =F8*G8 -> 50000 | J8: =F8*H8 -> 38000 | K8: =I8-J8 -> 12000 | L8: =IFERROR(K8/I8,0) -> 0.24
A9: 1008 | B9: 46092 | C9: West | D9: Headphones | E9: Accessories | F9: 12 | G9: 2000 | H9: 1200 | I9: =F9*G9 -> 24000 | J9: =F9*H9 -> 14400 | K9: =I9-J9 -> 9600 | L9: =IFERROR(K9/I9,0) -> 0.4
A10: 1009 | B10: 46101 | C10: North | D10: Monitor | E10: Electronics | F10: 5 | G10: 12000 | H10: 8500 | I10: =F10*G10 -> 60000 | J10: =F10*H10 -> 42500 | K10: =I10-J10 -> 17500 | L10: =IFERROR(K10/I10,0) -> 0.29166667
A11: 1010 | B11: 46116 | C11: South | D11: Keyboard | E11: Accessories | F11: 10 | G11: 1500 | H11: 900 | I11: =F11*G11 -> 15000 | J11: =F11*H11 -> 9000 | K11: =I11-J11 -> 6000 | L11: =IFERROR(K11/I11,0) -> 0.4
A12: 1011 | B12: 46127 | C12: East | D12: Mouse | E12: Accessories | F12: 20 | G12: 800 | H12: 400 | I12: =F12*G12 -> 16000 | J12: =F12*H12 -> 8000 | K12: =I12-J12 -> 8000 | L12: =IFERROR(K12/I12,0) -> 0.5
A13: 1012 | B13: 46137 | C13: West | D13: Laptop | E13: Electronics | F13: 2 | G13: 50000 | H13: 38000 | I13: =F13*G13 -> 100000 | J13: =F13*H13 -> 76000 | K13: =I13-J13 -> 24000 | L13: =IFERROR(K13/I13,0) -> 0.24

Sheet Financial_Model
A1: FINANCIAL PERFORMANCE MODEL
A3: Metric | B3: Value | C3: Interpretation
A4: Total Revenue | B4: =SUM(Sales_Data!I2:I13) -> 607000 | C4: Sales generated before costs
A5: Total Cost | B5: =SUM(Sales_Data!J2:J13) -> 437100 | C5: Direct product cost
A6: Total Profit | B6: =SUM(Sales_Data!K2:K13) -> 169900 | C6: Revenue less total cost
A7: Overall Profit Margin | B7: =IFERROR(B6/B4,0) -> 0.27990115 | C7: Profit as a share of revenue
A8: Total Units Sold | B8: =SUM(Sales_Data!F2:F13) -> 92 | C8: Total units across all orders
A9: Number of Orders | B9: =COUNTA(Sales_Data!A2:A13) -> 12 | C9: Count of order records
A12: Model checks
A13: Revenue check | B13: =IF(ABS(B4-SUMPRODUCT(Sales_Data!F2:F13,Sales_Data!G2:G13))<0.01,"PASS","CHECK") -> PASS
A14: Profit check | B14: =IF(ABS(B6-(B4-B5))<0.01,"PASS","CHECK") -> PASS
A16: Note | B16: All records are simulated for practice; not actual Arrowstack/company data.

Sheet Pivot_Dashboard
A1: EXECUTIVE FINANCIAL PERFORMANCE DASHBOARD
A3: Sample sales analysis | January–April 2026 | Values in Indian Rupees (₹)
A5: TOTAL REVENUE | D5: TOTAL PROFIT | G5: PROFIT MARGIN | J5: UNITS SOLD
A6: =SUM(Sales_Data!I2:I13) -> 607000 | D6: =SUM(Sales_Data!K2:K13) -> 169900 | G6: =IFERROR(SUM(Sales_Data!K2:K13)/SUM(Sales_Data!I2:I13),0) -> 0.27990115 | J6: =SUM(Sales_Data!F2:F13) -> 92
G24: KEY BUSINESS INSIGHTS
G25: • Highest revenue product: Laptop
G26: • Top region by profit: West
G27: • Revenue peaks in February in this sample
G28: • Overall margin is about 27.22%
G29: • Interpret findings in context: only 12 simulated orders.
A39: Important: dashboard charts are linked to formula-based summary sheets. Native PivotTables and slicers are not embedded by this generator; see Read_Me for the quick Excel steps to add them.
A42: Native PivotTables: see Native_Region_Pivot, Native_Product_Pivot and Native_Monthly_Pivot.
A43: Interactive Excel slicers must be added in desktop Excel; they are not supported by this automated export.

Sheet Region_Pivot
A1: REGIONAL PERFORMANCE SUMMARY
A3: Region | B3: Revenue (₹) | C3: Profit (₹) | D3: Units Sold
A4: East | B4: =SUMIF(Sales_Data!$C$2:$C$13,A4,Sales_Data!$I$2:$I$13) -> 78000 | C4: =SUMIF(Sales_Data!$C$2:$C$13,A4,Sales_Data!$K$2:$K$13) -> 24800 | D4: =SUMIF(Sales_Data!$C$2:$C$13,A4,Sales_Data!$F$2:$F$13) -> 29
A5: North | B5: =SUMIF(Sales_Data!$C$2:$C$13,A5,Sales_Data!$I$2:$I$13) -> 172000 | C5: =SUMIF(Sales_Data!$C$2:$C$13,A5,Sales_Data!$K$2:$K$13) -> 47500 | D5: =SUMIF(Sales_Data!$C$2:$C$13,A5,Sales_Data!$F$2:$F$13) -> 22
A6: South | B6: =SUMIF(Sales_Data!$C$2:$C$13,A6,Sales_Data!$I$2:$I$13) -> 83000 | C6: =SUMIF(Sales_Data!$C$2:$C$13,A6,Sales_Data!$K$2:$K$13) -> 28000 | D6: =SUMIF(Sales_Data!$C$2:$C$13,A6,Sales_Data!$F$2:$F$13) -> 24
A7: West | B7: =SUMIF(Sales_Data!$C$2:$C$13,A7,Sales_Data!$I$2:$I$13) -> 274000 | C7: =SUMIF(Sales_Data!$C$2:$C$13,A7,Sales_Data!$K$2:$K$13) -> 69600 | D7: =SUMIF(Sales_Data!$C$2:$C$13,A7,Sales_Data!$F$2:$F$13) -> 17
A10: Excel PivotTable practice
A11: This is a formula-based summary, not a native PivotTable. See Read_Me for how to create true PivotTables in Excel.

Sheet Product_Pivot
A1: PRODUCT PERFORMANCE SUMMARY
A3: Product | B3: Revenue (₹) | C3: Profit (₹) | D3: Units Sold
A4: Headphones | B4: =SUMIF(Sales_Data!$D$2:$D$13,A4,Sales_Data!$I$2:$I$13) -> 44000 | C4: =SUMIF(Sales_Data!$D$2:$D$13,A4,Sales_Data!$K$2:$K$13) -> 17600 | D4: =SUMIF(Sales_Data!$D$2:$D$13,A4,Sales_Data!$F$2:$F$13) -> 22
A5: Keyboard | B5: =SUMIF(Sales_Data!$D$2:$D$13,A5,Sales_Data!$I$2:$I$13) -> 27000 | C5: =SUMIF(Sales_Data!$D$2:$D$13,A5,Sales_Data!$K$2:$K$13) -> 10800 | D5: =SUMIF(Sales_Data!$D$2:$D$13,A5,Sales_Data!$F$2:$F$13) -> 18
A6: Laptop | B6: =SUMIF(Sales_Data!$D$2:$D$13,A6,Sales_Data!$I$2:$I$13) -> 400000 | C6: =SUMIF(Sales_Data!$D$2:$D$13,A6,Sales_Data!$K$2:$K$13) -> 96000 | D6: =SUMIF(Sales_Data!$D$2:$D$13,A6,Sales_Data!$F$2:$F$13) -> 8
A7: Monitor | B7: =SUMIF(Sales_Data!$D$2:$D$13,A7,Sales_Data!$I$2:$I$13) -> 108000 | C7: =SUMIF(Sales_Data!$D$2:$D$13,A7,Sales_Data!$K$2:$K$13) -> 31500 | D7: =SUMIF(Sales_Data!$D$2:$D$13,A7,Sales_Data!$F$2:$F$13) -> 9
A8: Mouse | B8: =SUMIF(Sales_Data!$D$2:$D$13,A8,Sales_Data!$I$2:$I$13) -> 28000 | C8: =SUMIF(Sales_Data!$D$2:$D$13,A8,Sales_Data!$K$2:$K$13) -> 14000 | D8: =SUMIF(Sales_Data!$D$2:$D$13,A8,Sales_Data!$F$2:$F$13) -> 35
A11: This is a formula-based summary, not a native PivotTable.

Sheet Monthly_Pivot
A1: MONTHLY PERFORMANCE SUMMARY
A3: Month | B3: Revenue (₹) | C3: Profit (₹)
A4: Jan | B4: =SUMPRODUCT((MONTH(Sales_Data!$B$2:$B$13)=1)*(YEAR(Sales_Data!$B$2:$B$13)=2026)*Sales_Data!$I$2:$I$13) -> 132000 | C4: =SUMPRODUCT((MONTH(Sales_Data!$B$2:$B$13)=1)*(YEAR(Sales_Data!$B$2:$B$13)=2026)*Sales_Data!$K$2:$K$13) -> 36800
A5: Feb | B5: =SUMPRODUCT((MONTH(Sales_Data!$B$2:$B$13)=2)*(YEAR(Sales_Data!$B$2:$B$13)=2026)*Sales_Data!$I$2:$I$13) -> 210000 | C5: =SUMPRODUCT((MONTH(Sales_Data!$B$2:$B$13)=2)*(YEAR(Sales_Data!$B$2:$B$13)=2026)*Sales_Data!$K$2:$K$13) -> 56000
A6: Mar | B6: =SUMPRODUCT((MONTH(Sales_Data!$B$2:$B$13)=3)*(YEAR(Sales_Data!$B$2:$B$13)=2026)*Sales_Data!$I$2:$I$13) -> 134000 | C6: =SUMPRODUCT((MONTH(Sales_Data!$B$2:$B$13)=3)*(YEAR(Sales_Data!$B$2:$B$13)=2026)*Sales_Data!$K$2:$K$13) -> 39100
A7: Apr | B7: =SUMPRODUCT((MONTH(Sales_Data!$B$2:$B$13)=4)*(YEAR(Sales_Data!$B$2:$B$13)=2026)*Sales_Data!$I$2:$I$13) -> 131000 | C7: =SUMPRODUCT((MONTH(Sales_Data!$B$2:$B$13)=4)*(YEAR(Sales_Data!$B$2:$B$13)=2026)*Sales_Data!$K$2:$K$13) -> 38000
A10: This is a formula-based summary, not a native PivotTable.

Sheet Read_Me
A1: PROJECT GUIDE & COMPLETION NOTES
A3: Purpose | B3: Excel financial modeling and dashboard practice using simulated sales data.
A4: Included | B4: Sales_Data, Financial_Model, Pivot_Dashboard, and formula-based Region_Pivot, Product_Pivot, Monthly_Pivot summaries.
A5: Important distinction | B5: The summary sheets are formula-based, not native Excel PivotTables. This workbook generator does not create true PivotTables or slicers.
A6: Create a real PivotTable | B6: On Sales_Data, click inside the SalesTable → Insert → PivotTable → New Worksheet. Add Region to Rows and Revenue and Profit to Values; set each Values field to Sum.
A7: Product PivotTable | B7: Repeat using Product in Rows and Revenue, Profit, Units_Sold in Values.
A8: Monthly PivotTable | B8: Repeat using Order_Date in Rows and Revenue and Profit in Values. Right-click a date → Group → Months and Years.
A9: Add slicer | B9: Click a native PivotTable → PivotTable Analyze → Insert Slicer → choose Region or Product.
A10: Refresh | B10: If source data changes, use Data → Refresh All. Formula-based summaries update automatically.
A11: Dataset | B11: 12 simulated sales records, January–April 2026. This is not actual Arrowstack or company data.
A12: Submission reminder | B12: Review calculations and add screenshots before uploading. Only claim native PivotTables/slicers after you create and test them in Excel.

Sheet Native_Region_Pivot
A1: NATIVE REGION PIVOT
A3: Filter
A5: Region | B5: Data
A6: East | B6: Sum - Revenue | C6: 78000
B7: Sum - Profit | C7: 24800
B8: Sum - Units_Sold | C8: 29
A9: North | B9: Sum - Revenue | C9: 172000
B10: Sum - Profit | C10: 47500
B11: Sum - Units_Sold | C11: 22
A12: South | B12: Sum - Revenue | C12: 83000
B13: Sum - Profit | C13: 28000
B14: Sum - Units_Sold | C14: 24
A15: West | B15: Sum - Revenue | C15: 274000
B16: Sum - Profit | C16: 69600
B17: Sum - Units_Sold | C17: 17
A18: Total Sum - Revenue | C18: 607000
A19: Total Sum - Profit | C19: 169900
A20: Total Sum - Units_Sold | C20: 92

Sheet Native_Product_Pivot
A1: NATIVE PRODUCT PIVOT
A3: Filter
A5: Product | B5: Data
A6: Headphones | B6: Sum - Revenue | C6: 44000
B7: Sum - Profit | C7: 17600
B8: Sum - Units_Sold | C8: 22
A9: Keyboard | B9: Sum - Revenue | C9: 27000
B10: Sum - Profit | C10: 10800
B11: Sum - Units_Sold | C11: 18
A12: Laptop | B12: Sum - Revenue | C12: 400000
B13: Sum - Profit | C13: 96000
B14: Sum - Units_Sold | C14: 8
A15: Monitor | B15: Sum - Revenue | C15: 108000
B16: Sum - Profit | C16: 31500
B17: Sum - Units_Sold | C17: 9
A18: Mouse | B18: Sum - Revenue | C18: 28000
B19: Sum - Profit | C19: 14000
B20: Sum - Units_Sold | C20: 35
A21: Total Sum - Revenue | C21: 607000
A22: Total Sum - Profit | C22: 169900
A23: Total Sum - Units_Sold | C23: 92

Sheet Native_Monthly_Pivot
A1: NATIVE MONTHLY PIVOT
A3: Filter
A5: Order_Date | B5: Data
A6: 46027 | B6: Sum - Revenue | C6: 100000
B7: Sum - Profit | C7: 24000
A8: 46034 | B8: Sum - Revenue | C8: 20000
B9: Sum - Profit | C9: 8000
A10: 46040 | B10: Sum - Revenue | C10: 12000
B11: Sum - Profit | C11: 4800
A12: 46056 | B12: Sum - Revenue | C12: 150000
B13: Sum - Profit | C13: 36000
A14: 46063 | B14: Sum - Revenue | C14: 12000
B15: Sum - Profit | C15: 6000
A16: 46072 | B16: Sum - Revenue | C16: 48000
B17: Sum - Profit | C17: 14000
A18: 46083 | B18: Sum - Revenue | C18: 50000
B19: Sum - Profit | C19: 12000
A20: 46092 | B20: Sum - Revenue | C20: 24000
B21: Sum - Profit | C21: 9600
A22: 46101 | B22: Sum - Revenue | C22: 60000
B23: Sum - Profit | C23: 17500
A24: 46116 | B24: Sum - Revenue | C24: 15000
B25: Sum - Profit | C25: 6000
A26: 46127 | B26: Sum - Revenue | C26: 16000
B27: Sum - Profit | C27: 8000
A28: 46137 | B28: Sum - Revenue | C28: 100000
B29: Sum - Profit | C29: 24000
A30: Total Sum - Revenue | C30: 607000
A31: Total Sum - Profit | C31: 169900
